autoclean/__init__.py
autoclean/cleaning.py
autoclean/engine.py
autoclean/report.py
autoclean/utils.py
autoclean_ds-0.1.0.dist-info/licenses/license
tests/cleaning_test.py
tests/test_engine.py
tests/test_missing.py
tests/test_outliers.py
autoclean_ds-0.1.0.dist-info/METADATA
autoclean_ds-0.1.0.dist-info/WHEEL
autoclean_ds-0.1.0.dist-info/top_level.txt
autoclean_ds-0.1.0.dist-info/RECORD
