Metadata-Version: 2.4
Name: autoclean-ds
Version: 0.1.0
Summary: Automated data cleaning library for pandas DataFrames
Home-page: https://github.com/jd878-gif/autoclean
Author: Jeet Dave
Author-email: Jeet Dave <jd.878@njit.edu>
Requires-Python: >=3.9
License-File: license
Requires-Dist: pandas>=1.5
Requires-Dist: numpy>=1.21
Dynamic: author
Dynamic: home-page
Dynamic: license-file
Dynamic: requires-python
